tf_agents/__init__.py
tf_agents/tf_agents_api_test.py
tf_agents/version.py
tf_agents/agents/__init__.py
tf_agents/agents/data_converter.py
tf_agents/agents/data_converter_test.py
tf_agents/agents/test_util.py
tf_agents/agents/tf_agent.py
tf_agents/agents/tf_agent_test.py
tf_agents/agents/behavioral_cloning/__init__.py
tf_agents/agents/behavioral_cloning/behavioral_cloning_agent.py
tf_agents/agents/behavioral_cloning/behavioral_cloning_agent_test.py
tf_agents/agents/categorical_dqn/__init__.py
tf_agents/agents/categorical_dqn/categorical_dqn_agent.py
tf_agents/agents/categorical_dqn/categorical_dqn_agent_test.py
tf_agents/agents/cql/__init__.py
tf_agents/agents/cql/cql_sac_agent.py
tf_agents/agents/cql/cql_sac_agent_test.py
tf_agents/agents/ddpg/__init__.py
tf_agents/agents/ddpg/actor_network.py
tf_agents/agents/ddpg/actor_network_test.py
tf_agents/agents/ddpg/actor_rnn_network.py
tf_agents/agents/ddpg/actor_rnn_network_test.py
tf_agents/agents/ddpg/critic_network.py
tf_agents/agents/ddpg/critic_network_test.py
tf_agents/agents/ddpg/critic_rnn_network.py
tf_agents/agents/ddpg/critic_rnn_network_test.py
tf_agents/agents/ddpg/ddpg_agent.py
tf_agents/agents/ddpg/ddpg_agent_test.py
tf_agents/agents/ddpg/examples/__init__.py
tf_agents/agents/ddpg/examples/v2/__init__.py
tf_agents/agents/ddpg/examples/v2/train_eval.py
tf_agents/agents/ddpg/examples/v2/train_eval_rnn.py
tf_agents/agents/dqn/__init__.py
tf_agents/agents/dqn/dqn_agent.py
tf_agents/agents/dqn/dqn_agent_test.py
tf_agents/agents/dqn/examples/__init__.py
tf_agents/agents/dqn/examples/v2/__init__.py
tf_agents/agents/dqn/examples/v2/train_eval.py
tf_agents/agents/dqn/examples/v2/train_eval_test.py
tf_agents/agents/ppo/__init__.py
tf_agents/agents/ppo/ppo_actor_network.py
tf_agents/agents/ppo/ppo_actor_network_test.py
tf_agents/agents/ppo/ppo_agent.py
tf_agents/agents/ppo/ppo_agent_test.py
tf_agents/agents/ppo/ppo_clip_agent.py
tf_agents/agents/ppo/ppo_kl_penalty_agent.py
tf_agents/agents/ppo/ppo_policy.py
tf_agents_nightly-0.20.0.dev20231221.dist-info/LICENSE
tf_agents_nightly-0.20.0.dev20231221.dist-info/METADATA
tf_agents_nightly-0.20.0.dev20231221.dist-info/WHEEL
tf_agents_nightly-0.20.0.dev20231221.dist-info/top_level.txt
tf_agents_nightly-0.20.0.dev20231221.dist-info/RECORD
