Metadata-Version: 2.1
Name: tf-agents-nightly
Version: 0.20.0.dev20231221
Summary: TF-Agents: A Reinforcement Learning Library for TensorFlow
Home-page: https://github.com/tensorflow/agents
Author: Google LLC
Author-email: no-reply@google.com
License: Apache 2.0
Keywords: tensorflow agents reinforcement learning machine bandits
Classifier: Development Status :: 3 - Alpha
Classifier: Intended Audience :: Developers
Classifier: Intended Audience :: Education
Classifier: Intended Audience :: Science/Research
Classifier: License :: OSI Approved :: Apache Software License
Classifier: Programming Language :: Python :: 3
Classifier: Programming Language :: Python :: 3.8
Classifier: Programming Language :: Python :: 3.9
Classifier: Programming Language :: Python :: 3.10
Classifier: Programming Language :: Python :: 3.11
Classifier: Topic :: Scientific/Engineering
Classifier: Topic :: Scientific/Engineering :: Mathematics
Classifier: Topic :: Scientific/Engineering :: Artificial Intelligence
Classifier: Topic :: Software Development
Classifier: Topic :: Software Development :: Libraries
Classifier: Topic :: Software Development :: Libraries :: Python Modules
Requires-Python: >=3
License-File: LICENSE
Requires-Dist: absl-py >=2.0.0
Requires-Dist: cloudpickle >=3.0.0
Requires-Dist: gin-config >=0.5.0
Requires-Dist: gym <=0.23.1,>=0.17.0
Requires-Dist: gymnasium >=0.29.0
Requires-Dist: numpy >=1.26.2
Requires-Dist: pillow >=10.1.0
Requires-Dist: six >=1.16.0
Requires-Dist: protobuf <=4.23.4,>=3.11.3
Requires-Dist: wrapt >=1.11.1
Requires-Dist: typing-extensions ==4.5.0
Requires-Dist: pygame ==2.5.2
Requires-Dist: tf-keras-nightly
Requires-Dist: tfp-nightly
Provides-Extra: reverb
Requires-Dist: rlds ; extra == 'reverb'
Requires-Dist: dm-reverb-nightly ; extra == 'reverb'
Requires-Dist: tf-nightly ; extra == 'reverb'
Provides-Extra: tests
Requires-Dist: mock >=2.0.0 ; extra == 'tests'
Requires-Dist: opencv-python >=3.4.1.15 ; extra == 'tests'
Requires-Dist: pybullet ; extra == 'tests'
Requires-Dist: scipy >=1.1.0 ; extra == 'tests'
